mcp_excalidraw_server_ranim.py
mcp_excalidraw_server_ranim-1.0.1.dist-info/METADATA
mcp_excalidraw_server_ranim-1.0.1.dist-info/WHEEL
mcp_excalidraw_server_ranim-1.0.1.dist-info/entry_points.txt
mcp_excalidraw_server_ranim-1.0.1.dist-info/top_level.txt
mcp_excalidraw_server_ranim-1.0.1.dist-info/RECORD
