Metadata-Version: 2.4
Name: mcp-excalidraw-server-ranim
Version: 1.0.1
Requires-Python: >=3.8
Requires-Dist: fastmcp
Dynamic: requires-dist
Dynamic: requires-python
